Workbook

Sheet Systems Summary
D2: Summary - Mr. Jay Immigration Lawyer Office | I2: Contractors’ Lic # 926663
D3: Version 1A
B5: Special Note: | D5: Complete Project Includes working 5 days/week for all trades under Bains Dev.
B7: Project: | D7: 356 S Daniel Way, San Jose, CA 95128 | F7: Project Type: | I7: TI
B8: Location: | D8: Close to Santana Row | F8: Structure Type: | I8: Tilt Up
F9: No. Stories Below Grade: | I9: NA
F10: No. Stories Above Grade: | I10: 1
F11: No. of Units: | I11: 2
B12: Architect: | D12: N/A | F12: No. of Bathrooms: | I12: 2
B13: Drawgings | D13: Drawings by Architects Julio
B15: Int. Design | F15: Off-Site Area: | I15: 0 | J15: SF
F16: TI Building Area: | I16: 8720 | J16: SF
B17: Est. Date: | D17: 44783 | F17: Lease Space/TI Area: | I17: 8720 | J17: SF
F18: Common Area: | I18: NA | J18: SF
B19: Contact: | D19: Vagish Kapila - (cell) 408-410-6151; vkapila@bainsdev.com | F19: Unit Area: | I19: NA | J19: SF
F20: Garage Area: | I20: NA | J20: SF
I22: TOTAL | J22: COST
B23: SECT | D23: DESCRIPTION | F23: Details | I23: COST | J23: PER SF
B25: 01000 | D25: Temporary Construction | I25: ='Off-Site Summary'!H17+'Site Summary'!H17+'Garage Summary'!H17+'Building Summary'!H22 -> 410 | J25: =I25/I17 -> 0.047018349
B26: ='Building Detail'!B26 -> 01100 | D26: ='Building Detail'!D26 -> Scaffold/Demo Scrapper | F26: ='Building Detail'!J26 -> NIC | I26: ='Building Detail'!H26 -> 0 | J26: ='Building Detail'!I35 -> 0
B27: ='Building Detail'!B27 -> 01200 | D27: ='Building Detail'!D27 -> Signs and Menu | F27: ='Building Detail'!J27 -> NIC | I27: ='Building Detail'!H27 -> 410 | J27: ='Building Detail'!I36 -> 0
B29: 02000 | D29: Site Work & Demolition | I29: ='Off-Site Summary'!H18+'Site Summary'!H18+'Garage Summary'!H18+'Building Summary'!H23 -> 117617 | J29: =I29/I17 -> 13.488188
B30: ='Building Detail'!B34 -> 02150 | D30: ='Building Detail'!D34 -> Demolition | F30: ='Building Detail'!J34 -> Includes inside demo for the space per the plan. Includes ceiling demo, all carpet to be removed and floor glue removed, demo of 2 bathrooms, demo all tiles in the bathroom. Includes asbestos demo allowance for $40k. Also includes demo of entire offices to make it an open ceiling design | I30: ='Building Detail'!H34 -> 83776
B31: ='Building Detail'!B35 -> 02175 | D31: ='Building Detail'!D35 -> Dewatering, Sidwalk Repair | F31: ='Building Detail'!J35 -> Includes demo of part of existing side walk to create a new ADA drive way per drawings | I31: ='Building Detail'!H35 -> 24970 | J31: ='Building Detail'!I40 -> 0
B32: ='Building Detail'!B36 -> 02180 | D32: ='Building Detail'!D36 -> Landscaping | I32: ='Building Detail'!H36 -> 0 | J32: ='Building Detail'!I41 -> 0
B33: ='Building Detail'!B37 -> 02190 | D33: ='Building Detail'!D37 -> Waterproofing | F33: ='Building Detail'!J37 -> May be needed for shower room | I33: ='Building Detail'!H37 -> 8871
B35: 03000 | D35: Concrete | I35: ='Off-Site Summary'!H19+'Site Summary'!H19+'Garage Summary'!H19+'Building Summary'!H24 -> 73149 | J35: =I35/I17 -> 8.3886468
B36: ='Building Detail'!B43 -> 03100 | D36: ='Building Detail'!D43 -> Asphalt/Striping/Seting | I36: ='Building Detail'!H43 -> 11710 | J36: ='Building Detail'!I44 -> 0
B37: ='Building Detail'!B44 -> 03200 | D37: ='Building Detail'!D44 -> Concrete Cutting/Pouring/Coring | F37: ='Building Detail'!J44 -> Includes new coring for shower room and sauna | I37: ='Building Detail'!H44 -> 18779 | J37: ='Building Detail'!I45 -> 0
B38: ='Building Detail'!B45 -> 03400 | D38: ='Building Detail'!D45 -> Repair/Rebuild Side Walks | F38: ='Building Detail'!J45 -> Includes new sidewalk, w/o handrail to be build for ADA access and create a new enterance to the new door/space | I38: ='Building Detail'!H45 -> 42660 | J38: ='Building Detail'!I46 -> 0
B39: ='Building Detail'!B46 -> 03500 | D39: ='Building Detail'!D46 -> Stucco | I39: ='Building Detail'!H46 -> 0 | J39: ='Building Detail'!I47 -> 0
B41: ='Building Detail'!B50 -> 05000 | D41: ='Building Detail'!D50 -> STEEL/MASONRY/STRUCTURAL | F41: ='Building Detail'!J56 -> Includes structural support for 3 new HVAC units on the roof | I41: ='Building Detail'!H58 -> 60180 | J41: ='Building Detail'!I58 -> 6.9013761
B42: ='Building Detail'!B51 -> 05200 | D42: ='Building Detail'!D51 -> Miscellaneous/Decorative metals | F42: ='Building Detail'!J51 -> NIC | I42: ='Building Detail'!H51 -> 0
B43: ='Building Detail'!B52 -> 05300 | D43: ='Building Detail'!D52 -> Steel stairs | F43: ='Building Detail'!J52 -> Includes repairing of current stairs to a new floating stairs | I43: ='Building Detail'!H52 -> 19334
B44: ='Building Detail'!B53 -> 05400 | D44: ='Building Detail'!D53 -> Cultured Stone - Façade & Planter Caps | F44: ='Building Detail'!J53 -> Includes new stones in the lobby area | I44: ='Building Detail'!H53 -> 29445
B45: ='Building Detail'!B54 -> 05500 | D45: ='Building Detail'!D54 -> Metal Awning | F45: ='Building Detail'!J54 -> N/A | I45: ='Building Detail'!H54 -> 0
B46: ='Building Detail'!B55 -> 05600 | D46: ='Building Detail'!D55 -> Repair Concrete floor | F46: ='Building Detail'!J55 -> Includes minor crack/repiar on the 2nd floor after remoing old carpet | I46: ='Building Detail'!H55 -> 3271
B47: ='Building Detail'!B56 -> 05700 | D47: ='Building Detail'!D56 -> Sturctural Support | F47: ='Building Detail'!J56 -> Includes structural support for 3 new HVAC units on the roof | I47: ='Building Detail'!H56 -> 8130
B49: ='Building Detail'!B60 -> 55000 | D49: ='Building Detail'!D60 -> Carpentry | I49: ='Building Detail'!H66 -> 10710 | J49: =I49/I17 -> 1.228211
B50: ='Building Detail'!B61 -> 05510 | D50: ='Building Detail'!D69 -> Rough Framing | F50: ='Building Detail'!J61 -> Rough carpentry needed to repair minor ceiling grids. Repair only. Repair in 6 areas included | I50: ='Building Detail'!H61 -> 10710
B51: ='Building Detail'!B62 -> 05510 | D51: ='Building Detail'!D70 -> Finish Carpentry | F51: ='Building Detail'!J62 -> . | I51: ='Building Detail'!H62 -> 0
B53: 06000 | D53: Wood / Plastics | I53: ='Off-Site Summary'!H22+'Site Summary'!H22+'Garage Summary'!H22+'Building Summary'!H26 -> 41085 | J53: =I53/I17 -> 4.7115826
B54: ='Building Detail'!B69 -> 06100 | D54: ='Building Detail'!D69 -> Rough Framing | F54: ='Building Detail'!J69 -> Includes rough framing to support cabinets and other items | I54: ='Building Detail'!H69 -> 28790
B55: ='Building Detail'!B70 -> 06120 | D55: ='Building Detail'!D70 -> Finish Carpentry | F55: ='Building Detail'!J70 -> Includes creating open ceiling Lounge area, backing for TV, and special rough carpentry for the lobby area | I55: ='Building Detail'!H70 -> 7908
B56: ='Building Detail'!B71 -> 06200 | D56: ='Building Detail'!D71 -> Millworkand Casework | F56: ='Building Detail'!J71 -> Includes all material, countertop, cabinets, benches woodwork and installation for the screen, railing and any other millwork | I56: ='Building Detail'!H71 -> 0
B57: ='Building Detail'!B72 -> 06500 | D57: ='Building Detail'!D72 -> Millwork Extras - Handles, Metal, Cushion | I57: ='Building Detail'!H72 -> 0
B58: ='Building Detail'!B73 -> 06700 | D58: ='Building Detail'!D73 -> Countertops | F58: ='Building Detail'!J73 -> Countertop for the new millwork and cabinets | I58: ='Building Detail'!H73 -> 0
B59: ='Building Detail'!B74 -> 06800 | D59: ='Building Detail'!D74 -> Roofing | F59: ='Building Detail'!J74 -> NIC | I59: ='Building Detail'!H74 -> 0
B60: ='Building Detail'!B75 -> 06900 | D60: ='Building Detail'!D75 -> Steel Countertops | I60: ='Building Detail'!H75 -> 0
B61: ='Building Detail'!B76 -> 06950 | D61: ='Building Detail'!D76 -> Misc. Labor | F61: ='Building Detail'!J76 -> Includes misc labor for the duration of the job | I61: ='Building Detail'!H76 -> 4387
B63: 07000 | D63: THERMAL / MOISTURE PROTECT | I63: ='Building Detail'!H89 -> 15721 | J63: ='Building Detail'!I89 -> 1.802867
B64: ='Building Detail'!B83 -> 07100 | D64: ='Building Detail'!D83 -> Building/Inside Wall Insulation | F64: ='Building Detail'!J83 -> May be needed on the 2nd floor area | I64: ='Building Detail'!H83 -> 12270
B65: ='Building Detail'!B84 -> 07200 | D65: ='Building Detail'!D84 -> Exterior Wall Insulation | I65: ='Building Detail'!H84 -> 0
B66: ='Building Detail'!B85 -> 72500 | D66: ='Building Detail'!D85 -> Ceiling Insulations | I66: ='Building Detail'!H85 -> 0
B67: ='Building Detail'!B86 -> 07300 | D67: ='Building Detail'!D86 -> Fire Caulking | F67: ='Building Detail'!J86 -> Fire caulking 1st floor exit corridor | I67: ='Building Detail'!H86 -> 3451
B69: 08000 | D69: DOORS / GLASS | I69: ='Building Detail'!H98 -> 89423.7
B70: ='Building Detail'!B93 -> 08100 | D70: ='Building Detail'!D93 -> Door/Frame/Hardware | F70: ='Building Detail'!J93 -> 2 new exterior doors per drawings, 8 new 3o7o doors per architect with framing (non fire rated) standard commercial doors | I70: ='Building Detail'!H93 -> 24054
B71: ='Building Detail'!B94 -> 08150 | D71: ='Building Detail'!D94 -> Storefront Window and Door/Glass | F71: ='Building Detail'!J94 -> Includes new storefront glass for around stair case and 4 new offices for the lawyer areas. Includes full height glass offices w/o sheetrock walls. Also includes a new Glass door to replace enterance door from the parking lot area to the office | I71: ='Building Detail'!H94 -> 65369.7
B72: ='Building Detail'!B95 -> 08200 | D72: ='Building Detail'!D95 -> Vinyl Film/Rollup Doors | I72: ='Building Detail'!H95 -> 0
B74: 09000 | D74: FINISHES- WALLS/FRAMES/CEILING/PAINTING | I74: ='Building Detail'!H115 -> 185839.9 | J74: =I74/I17 -> 21.311915
B75: ='Building Detail'!B102 -> 09200 | D75: ='Building Detail'!D102 -> Interior Metal Stud Framing + Gypboard (Full Height) | F75: ='Building Detail'!J102 -> New walls and framing per drawings. Also includes new soffit work around the 4 new offices and lobby area. Includes new header for all glass storefront offices | I75: ='Building Detail'!H102 -> 37888
B76: ='Building Detail'!B103 -> 09200 | D76: ='Building Detail'!D103 -> Interior Metal Stud Framing + Gypboard | I76: ='Building Detail'!H103 -> 0
B77: ='Building Detail'!B104 -> 09250 | D77: ='Building Detail'!D104 -> Sound walls - staggered studs | I77: ='Building Detail'!H104 -> 0
B78: ='Building Detail'!B105 -> 09550 | D78: ='Building Detail'!D105 -> Acoustical/Hardlid Ceilings-w/seismic+bracing | F78: ='Building Detail'!J105 -> Includes replacing ceiling tiles only for the entire 2 floors, includes material | I78: ='Building Detail'!H105 -> 31851.9
B79: ='Building Detail'!B106 -> 09310 | D79: ='Building Detail'!D106 -> Ceramic tile floors/Walls/Front counter | F79: ='Building Detail'!J106 -> Includes new tile standard commercial install in the store and wood base around the front office area only. Includes new wall and floor tiles for the bathrooms as well. Standard commercial includes 4 ft high | I79: ='Building Detail'!H106 -> 37660
B80: ='Building Detail'!B107 -> 09550 | D80: ='Building Detail'!D107 -> Carpet/Vinyl Flooring | F80: ='Building Detail'!J107 -> NIC | I80: ='Building Detail'!H107 -> 0
B81: ='Building Detail'!B108 -> 09555 | D81: ='Building Detail'!D108 -> Hardwood floor | F81: ='Building Detail'!J108 -> New front lounge area hardwood floor and wood base standard commercial | I81: ='Building Detail'!H108 -> 14640
B82: ='Building Detail'!B109 -> 09650 | D82: ='Building Detail'!D109 -> Resilient flooring, Epoxy & Patio | F82: ='Building Detail'!J109 -> Includes new wood floor for the entire top office areas | I82: ='Building Detail'!H109 -> 23760
B83: ='Building Detail'!B110 -> 09900 | D83: ='Building Detail'!D110 -> Paint | F83: ='Building Detail'!J110 -> Includes paint on new walls in the new office area, side walls, outside building | I83: ='Building Detail'!H110 -> 40040
B85: 10000 | D85: ='Building Detail'!D118 -> SPECIALTIES (Accessories/Fire Alarm/Hood) | F85: ='Building Detail'!J124 -> . | I85: ='Building Detail'!H126 -> 18089 | J85: ='Building Detail'!I126 -> 2.0744266
B86: ='Building Detail'!B119 -> 10100 | D86: ='Building Detail'!D119 -> Bathroom Accessories | F86: ='Building Detail'!J119 -> Includes 2 new ADA bathrooms on both floors | I86: ='Building Detail'!H119 -> 1372
B87: ='Building Detail'!B120 -> 10200 | D87: ='Building Detail'!D120 -> Partitions/Showerpan | F87: ='Building Detail'!J120 -> Includes new shower pan, shower head and shower plumbing for the new shower room area | I87: ='Building Detail'!H120 -> 9217
B88: ='Building Detail'!B121 -> 10300 | D88: ='Building Detail'!D121 -> New Hood/Exhaust/Fire Systems | F88: ='Building Detail'!J121 -> NIC | I88: ='Building Detail'!H121 -> 0
B89: ='Building Detail'!B122 -> 10400 | D89: ='Building Detail'!D122 -> Fountain | F89: ='Building Detail'!J122 -> 0 | I89: ='Building Detail'!H122 -> 0
B90: ='Building Detail'!B123 -> 10500 | D90: ='Building Detail'!D123 -> Fire Alarm | F90: ='Building Detail'!J123 -> Includes fire alarm systems for both floors | I90: ='Building Detail'!H123 -> 7500
B91: ='Building Detail'!B124 -> 10600 | D91: ='Building Detail'!D124 -> FRP | F91: ='Building Detail'!J124 -> . | I91: ='Building Detail'!H124 -> 0
B93: 11000 | D93: EQUIPMENT | F93: ='Building Detail'!J131 -> Includes fire extingushier for the space per fire department standards | I93: ='Building Detail'!H136 -> 1600
B94: ='Building Detail'!B130 -> 11005 | D94: ='Building Detail'!D130 -> Projector Screen/White board/Furniture | I94: ='Building Detail'!H130 -> 0
B95: ='Building Detail'!B131 -> 11010 | D95: ='Building Detail'!D131 -> Fire extinghusier & Knox Box | F95: ='Building Detail'!J131 -> Includes fire extingushier for the space per fire department standards | I95: ='Building Detail'!H131 -> 1600
B97: 12000 | D97: ='Building Detail'!D139 -> FURNISHINGS/TRASH REMOVAL | F97: Includes trash dump per city requirements | I97: ='Off-Site Summary'!H28+'Site Summary'!H28+'Garage Summary'!H28+'Building Summary'!H32 -> 16077.6 | J97: =I97/I17 -> 1.8437615
B98: ='Building Detail'!B140 -> 12100 | D98: ='Building Detail'!D140 -> Trash Removal and Disposing | I98: ='Building Detail'!H140 -> 16077.6
B99: ='Building Detail'!B141 -> 12100 | D99: ='Building Detail'!D141 -> Signs | I99: ='Building Detail'!H141 -> 0
B101: 14000 | D101: Conveying Systems | I101: ='Off-Site Summary'!H30+'Site Summary'!H30+'Garage Summary'!H30+'Building Summary'!H33 -> 0 | J101: =I101/I17 -> 0
B102: 15000 | D102: Mechanical | I102: ='Off-Site Summary'!H31+'Site Summary'!H31+'Garage Summary'!H31+'Building Summary'!H34 -> 131913 | J102: =I102/I17 -> 15.127638
B103: ='Building Detail'!B151 -> 15500 | D103: ='Building Detail'!D151 -> HVAC | F103: ='Building Detail'!J151 -> Includes 3 new HVAC units. Includes repairing 5 existing units to current standards. Air balancing | I103: ='Building Detail'!H151 -> 131913
B104: ='Building Detail'!B152 -> 15540 | D104: ='Building Detail'!D152 -> Sheet Metal | I104: ='Building Detail'!H152 -> 0
B106: 151000 | D106: ='Building Detail'!D157 -> Fire sprinkler system | I106: ='Building Detail'!H157 -> 0 | J106: ='Building Detail'!I160 -> 0
B107: ='Building Detail'!B158 -> 15100 | D107: ='Building Detail'!D158 -> ALT: Raise FS from 9' to 10' Rm 526 | F107: ='Building Detail'!J157 -> No Fire Sprinklers needed
B109: 153000 | D109: ='Building Detail'!D162 -> Plumbing | I109: ='Building Detail'!H166 -> 67788.5 | J109: ='Building Detail'!I166 -> 7.7739106
B110: ='Building Detail'!B163 -> 15300 | D110: ='Building Detail'!D163 -> Plumbing | F110: ='Building Detail'!J163 -> Includes new plumbing for 2 new ADA bathrooms. Includes removing all plumbing on all bathrooms to install new tiles and put back plumbing fixtures in the same locations. Includes new plumbing for Sauna and Shower room | I110: ='Building Detail'!H163 -> 48254
B111: ='Building Detail'!B164 -> 15350 | D111: ='Building Detail'!D164 -> Plumbing Fixtures/Rough Material | F111: ='Building Detail'!J164 -> Includes plumbing fixtures per drawings for ADA bathroom and replace 2 broken fixtures in mens | I111: ='Building Detail'!H164 -> 19534.5
B112: 16000 | D112: Electrical | I112: ='Off-Site Summary'!H32+'Site Summary'!H32+'Garage Summary'!H32+'Building Summary'!H36 -> 267820.8 | J112: =I112/I17 -> 30.713394
B113: ='Building Detail'!B169 -> 16100 | D113: ='Building Detail'!D169 -> Building Electrical (sf) | F113: ='Building Detail'!J169 -> New electrical and power per drawings for the bathroom and lounge area. Includes T24 final test and reports. Replace all fixtures in the entire floors. Includes rewire new offices and layout. Includes new power and wiring for open office areas | I113: ='Building Detail'!H169 -> 189957.3
B114: ='Building Detail'!B170 -> 16200 | D114: ='Building Detail'!D170 -> Electrical (Building Interior Fixtures) | F114: ='Building Detail'!J170 -> Includes new lights (downlights) in the lobby area and reconfiguring power/wiring for the new office layouts and safeoff during construction | I114: ='Building Detail'!H170 -> 21961.5
B115: ='Building Detail'!B171 -> 16300 | D115: ='Building Detail'!D171 -> Electrical (Special Interior Work) | F115: ='Building Detail'!J171 -> Includes making all receptacles reframe and reinstall to ADA height. Approx. Over 200 receptacples. May require to rewire all receptacles in the entire builidng and both floors | I115: ='Building Detail'!H171 -> 55902
B117: 17000 | D117: Fire Life Safety | I117: ='Building Detail'!H183 -> 6268
B118: ='Building Detail'!B177 -> 17100 | D118: ='Building Detail'!D177 -> Fire life safety | F118: ='Building Detail'!J183 -> Includes new Fire life safety connection put new FLS in the new exit hallway | I118: ='Building Detail'!H177 -> 6268 | J118: =I118/I17 -> 0.71880734
B119: 18000 | D119: Architect | F119: NIC | I119: 0 | J119: -
D123: Subtotal | I123: =SUM(I93+I85+I117+I112+I109+I102+I97+I74+I63+I53+I41+I35+I29+I25+I69+I119+I49+I106) -> 1103692.5
L124: =I123-'Building Detail'!H186 -> 0
...

Sheet Building Summary
B7: Project: | D7: ='Systems Summary'!D12 -> N/A | E7: Project Type: | H7: TI
B8: Location: | D8: ='Systems Summary'!D8 -> Close to Santana Row | E8: Structure Type: | H8: Steel Frame
D9: ='Systems Summary'!D9 -> 0 | E9: No. Stories Below Grade: | H9: NA
E10: No. Stories Above Grade: | H10: 5
E11: No. of Units: | H11: NA
B12: Architect: | D12: Allied Architects | E12: No. of Bathrooms: | H12: NA
B13: Drawgings | D13: ='Systems Summary'!D13 -> Drawings by Architects Julio
D14: 3.0, 4.0, 4.1, 4.3, 4.4, 4.5, 5, 5.1, 5.2
B15: Int. Design | E15: Off-Site Area: | H15: NA | I15: SF
E16: Lease Space/TI Area: | H16: 5802 | I16: SF
B17: Est. Date: | D17: 40774 | E17: Gross Building Area: | H17: 5802 | I17: SF
E18: Common Area: | H18: NA | I18: SF
B20: SECT | D20: DESCRIPTION | E20: QUANT | F20: UNIT | G20: COST | H20: COST | I20: PER SF
B22: 01000 | D22: Temporary Construction | H22: ='Building Detail'!H30 -> 410
B23: 02000 | D23: Site Work & Demolition | H23: ='Building Detail'!H39 -> 117617
B24: 03000 | D24: Concrete | H24: ='Building Detail'!H48 -> 73149
B25: 05000 | D25: Steel | H25: ='Building Detail'!H58 -> 60180
B26: 06000 | D26: Wood / Plastics | H26: ='Building Detail'!H79 -> 41085
B27: 07000 | D27: Thermal / Moisture Protection | H27: ='Building Detail'!H89 -> 15721
B28: 08000 | D28: Doors / Glass | H28: ='Building Detail'!H98 -> 89423.7
B29: 09000 | D29: Finishes | H29: ='Building Detail'!H115 -> 185839.9
B30: 10000 | D30: Specialties | H30: ='Building Detail'!H126 -> 18089
B31: 11000 | D31: Equipment | H31: ='Building Detail'!H136 -> 1600
B32: 12000 | D32: Furnishings | H32: ='Building Detail'!H144 -> 16077.6
B33: 14000 | D33: Conveying Systems | H33: ='Building Detail'!H147 -> 0
B34: 15000 | D34: Mechanical | H34: ='Building Detail'!H155 -> 131913
B35: ='Building Detail'!B162 -> 152000 | D35: ='Building Detail'!D162 -> Plumbing | H35: ='Building Detail'!H162 -> 0
B36: 16000 | D36: Electrical | H36: ='Building Detail'!H174 -> 267820.8
D39: Subtotal | H39: =SUM(H21:H37) -> 1018926
D41: General Conditions
D42: Builders Risk Insurance
D43: General Liability Insurance
D44: Bond
D45: Overhead
D46: Contractor's Fee
D49: Subtotal | H49: =SUM(H38:H47) -> 1018926
D51: Contractor's Contingency
D54: BUILDING TOTAL COST | H54: =SUM(H48:H52) -> 1018926

Sheet Building Detail
D3: Building Bid DETAILS Sheet
B7: Project: | D7: ='Systems Summary'!D7 -> 356 S Daniel Way, San Jose, CA 95128 | E7: Project Type: | H7: TI
B8: Location: | D8: ='Systems Summary'!D8 -> Close to Santana Row | E8: Structure Type: | H8: Conc Block
E9: No. Stories Below Grade: | H9: NA
D10: San Jose, CA | E10: No. Stories Above Grade: | H10: 1
E11: No. of Units: | H11: NA
B12: Architect: | D12: ='Systems Summary'!D12 -> N/A | E12: No. of Bathrooms: | H12: NA
B13: Drawgings | D13: ='Systems Summary'!D13 -> Drawings by Architects Julio
B15: Int. Design | E15: Off-Site Area: | H15: NA | I15: SF
E16: Lease Space/TI Area: | H16: ='Systems Summary'!I16 -> 8720 | I16: SF
B17: Est. Date: | D17: ='Systems Summary'!D17 -> 44783 | E17: Gross Building Area: | H17: ='Systems Summary'!I17 -> 8720 | I17: SF | K17: Change Date
E18: Common Area: | H18: NA | I18: SF
B19: Contact: | D19: Vagish Kapila - (cell) 408-410-6151; vkpaila@bainsdev.com | E19: Unit Area: | H19: NA | I19: SF
D20: Raj - (cell) 510-432-8288; raj@bainsdev.com | E20: Garage Area: | H20: NA | I20: SF
H22: TOTAL | I22: COST | J22: Details
B23: SECT | D23: DESCRIPTION | E23: Details | H23: COST | I23: PER SF
B25: 01000 | D25: TEMPORARY CONSTRUCTION
B26: 01100 | D26: Scaffold/Demo Scrapper | E26: 0 | F26: SF | G26: 3 | H26: =G26*E26*38% -> 0 | J26: NIC
B27: 01200 | D27: Signs and Menu | E27: 1 | F27: SF | G27: 410 | H27: =G27*E27 -> 410 | J27: NIC
D30: Temporary Construction Totals | H30: =SUM(H25:H28) -> 410 | I30: =H30/H17 -> 0.047018349
B33: 02000 | D33: SITE WORK
B34: 02150 | D34: Demolition | E34: 1 | F34: LS | G34: 83776 | H34: =E34*G34 -> 83776 | J34: Includes inside demo for the space per the plan. Includes ceiling demo, all carpet to be removed and floor glue removed, demo of 2 bathrooms, demo all tiles in the bathroom. Includes asbestos demo allowance for $40k. Also includes demo of entire offices to make it an open ceiling design
B35: 02175 | D35: Dewatering, Sidwalk Repair | E35: 1 | F35: SF | G35: 24970 | H35: =E35*G35 -> 24970 | J35: Includes demo of part of existing side walk to create a new ADA drive way per drawings
B36: 02180 | D36: Landscaping | E36: 0 | F36: LS | G36: 5400 | H36: =E36*G36 -> 0
B37: 02190 | D37: Waterproofing | E37: 1 | F37: LS | G37: 8871 | H37: =E37*G37 -> 8871 | J37: May be needed for shower room
D39: Site Work Totals | H39: =SUM(H33:H37) -> 117617 | I39: =H39/H17 -> 13.488188
B42: 03000 | D42: CONCRETE/STUCCO/ASHPALT
B43: 03100 | D43: Asphalt/Striping/Seting | E43: 1 | F43: LS | G43: 11710 | H43: =E43*G43 -> 11710 | J43: Includes re-stripping of the back parking lot and shaving just the ADA parking spot
B44: 03200 | D44: Concrete Cutting/Pouring/Coring | E44: 1 | F44: LS | G44: 18779 | H44: =E44*G44 -> 18779 | J44: Includes new coring for shower room and sauna
B45: 03400 | D45: Repair/Rebuild Side Walks | E45: 1 | F45: LS | G45: 42660 | H45: =E45*G45 -> 42660 | J45: Includes new sidewalk, w/o handrail to be build for ADA access and create a new enterance to the new door/space
B46: 03500 | D46: Stucco | E46: 0 | F46: LS | G46: 12800 | H46: =E46*G46 -> 0
D48: Concrete Totals | H48: =SUM(H42:H46) -> 73149 | I48: =H48/H17 -> 8.3886468
B50: 05000 | D50: STEEL/MASONRY/STRUCTURAL
B51: 05200 | D51: Miscellaneous/Decorative metals | E51: 0 | F51: LS | G51: 5500 | H51: =E51*G51 -> 0 | J51: NIC
B52: 05300 | D52: Steel stairs | E52: 1 | F52: FLT | G52: 19334 | H52: =E52*G52 -> 19334 | J52: Includes repairing of current stairs to a new floating stairs
B53: 05400 | D53: Cultured Stone - Façade & Planter Caps | E53: 1 | F53: LS | G53: 29445 | H53: =E53*G53 -> 29445 | J53: Includes new stones in the lobby area
B54: 05500 | D54: Metal Awning | E54: 0 | F54: LS | G54: 3200 | H54: =E54*G54 -> 0 | J54: N/A
B55: 05600 | D55: Repair Concrete floor | E55: 1 | F55: LS | G55: 3271 | H55: =E55*G55 -> 3271 | J55: Includes minor crack/repiar on the 2nd floor after remoing old carpet
B56: 05700 | D56: Sturctural Support | E56: 3 | F56: LF | G56: 2710 | H56: =E56*G56 -> 8130 | J56: Includes structural support for 3 new HVAC units on the roof
D58: Steel Totals | H58: =SUM(H51:H56) -> 60180 | I58: =H58/H17 -> 6.9013761
B60: 55000 | D60: Carpentry
B61: 05510 | D61: Rough Carpentry | E61: 1 | F61: LS | G61: 10710 | H61: =E61*G61 -> 10710 | J61: Rough carpentry needed to repair minor ceiling grids. Repair only. Repair in 6 areas included
B62: 05510 | D62: Special Carpentry | F62: FLT | H62: =E62*G62 -> 0 | J62: .
F63: FLT | H63: =E63*G63 -> 0
D66: Carpentry Totals | H66: =SUM(H61:H64) -> 10710 | I66: =H66/H17 -> 1.228211
B68: 06000 | D68: WOOD / PLASTICS
B69: 06100 | D69: Rough Framing | E69: 1 | F69: LS | G69: 28790 | H69: =E69*G69 -> 28790 | J69: Includes rough framing to support cabinets and other items
B70: 06120 | D70: Finish Carpentry | E70: 1 | F70: LS | G70: 7908 | H70: =E70*G70 -> 7908 | J70: Includes creating open ceiling Lounge area, backing for TV, and special rough carpentry for the lobby area
B71: 06200 | D71: Millworkand Casework | E71: 0 | F71: LF | G71: 30570 | H71: =E71*G71 -> 0 | J71: Includes all material, countertop, cabinets, benches woodwork and installation for the screen, railing and any other millwork
B72: 06500 | D72: Millwork Extras - Handles, Metal, Cushion | E72: 0 | F72: LS | G72: 5412 | H72: =E72*G72 -> 0 | J72: Includes extra we got from millwork sub
B73: 06700 | D73: Countertops | E73: 0 | F73: UNIT | G73: 8200 | H73: =E73*G73 -> 0 | J73: Countertop for the new millwork and cabinets
B74: 06800 | D74: Roofing | E74: 0 | F74: LS | G74: 4900 | H74: =E74*G74 -> 0 | J74: NIC
B75: 06900 | D75: Steel Countertops | E75: 0 | F75: LF | G75: 7400 | H75: =E75*G75 -> 0 | J75: NIC
B76: 06950 | D76: Misc. Labor | E76: 1 | F76: LS | G76: 4387 | H76: =E76*G76 -> 4387 | J76: Includes misc labor for the duration of the job
D79: Wood / Plastics Totals | H79: =SUM(H69:H77) -> 41085 | I79: =H79/H17 -> 4.7115826
B82: 07000 | D82: THERMAL / MOISTURE PROTECT
B83: 07100 | D83: Building/Inside Wall Insulation | E83: 3 | F83: LS | G83: 4090 | H83: =E83*G83*100% -> 12270 | J83: May be needed on the 2nd floor area
B84: 07200 | D84: Exterior Wall Insulation | F84: SFCA | H84: =E84*G84 -> 0
B85: 72500 | D85: Ceiling Insulations | E85: 0 | F85: LS | G85: 517 | H85: =E85*G85 -> 0
B86: 07300 | D86: Fire Caulking | E86: 1 | F86: LS | G86: 3451 | H86: =E86*G86 -> 3451 | J86: Fire caulking 1st floor exit corridor
D89: Thermal / Moisture Protect Totals | H89: =SUM(H83:H87) -> 15721 | I89: =H89/H17 -> 1.802867
B92: 08000 | D92: DOORS / GLASS
B93: 08100 | D93: Door/Frame/Hardware | E93: 2 | F93: LS | G93: =4171+8*982 -> 12027 | H93: =E93*G93*100% -> 24054 | J93: 2 new exterior doors per drawings, 8 new 3o7o doors per architect with framing (non fire rated) standard commercial doors
B94: 08150 | D94: Storefront Window and Door/Glass | E94: 3.3 | F94: LS | G94: 19809 | H94: =E94*G94 -> 65369.7 | J94: Includes new storefront glass for around stair case and 4 new offices for the lawyer areas. Includes full height glass offices w/o sheetrock walls. Also includes a new Glass door to replace enterance door from the parking lot area to the office
B95: 08200 | D95: Vinyl Film/Rollup Doors | E95: 0 | F95: LS | G95: 2900 | H95: =E95*G95*38% -> 0
D98: Doors / Glass Totals | H98: =SUM(H93:H96) -> 89423.7 | I98: =H98/H17 -> 10.255011
B101: 09000 | D101: FINISHES- WALLS/FRAMES/CEILING/PAINTING
B102: 09200 | D102: Interior Metal Stud Framing + Gypboard (Full Height) | E102: 256 | F102: LF | G102: 148 | H102: =E102*G102 -> 37888 | J102: New walls and framing per drawings. Also includes new soffit work around the 4 new offices and lobby area. Includes new header for all glass storefront offices
B103: 09200 | D103: Interior Metal Stud Framing + Gypboard | E103: 0 | F103: LF | G103: 97 | H103: =E103*G103 -> 0
B104: 09250 | D104: Sound walls - staggered studs | F104: SF | H104: =E104*G104 -> 0
B105: 09550 | D105: Acoustical/Hardlid Ceilings-w/seismic+bracing | E105: 6777 | F105: SF | G105: 4.7 | H105: =E105*G105 -> 31851.9 | J105: Includes replacing ceiling tiles only for the entire 2 floors, includes material | K105: 21000
B106: 09310 | D106: Ceramic tile floors/Walls/Front counter | E106: 1.4 | F106: LS | G106: 26900 | H106: =G106*E106 -> 37660 | J106: Includes new tile standard commercial install in the store and wood base around the front office area only. Includes new wall and floor tiles for the bathrooms as well. Standard commercial includes 4 ft high | K106: Added ceramic tiles to bid. Reduced carpet and hardwood numbers and made allowances
B107: 09550 | D107: Carpet/Vinyl Flooring | E107: 0 | F107: LS | G107: 11996 | H107: =G107*E107 -> 0 | I107: Allowance | J107: NIC
B108: 09555 | D108: Hardwood floor | E108: 2 | F108: LS | G108: 7320 | H108: =G108*E108 -> 14640 | I108: Allowance | J108: New front lounge area hardwood floor and wood base standard commercial
B109: 09650 | D109: Resilient flooring, Epoxy & Patio | E109: 8000 | F109: SF | G109: 2.97 | H109: =G109*E109 -> 23760 | J109: Includes new wood floor for the entire top office areas
B110: 09900 | D110: Paint | E110: 13 | F110: LS | G110: 3080 | H110: =E110*G110 -> 40040 | J110: Includes paint on new walls in the new office area, side walls, outside building
B111: 09900 | D111: Paint - ceilings | F111: SF | H111: =E111*G111 -> 0
B112: 09950
D115: Finishes Totals | H115: =SUM(H102:H113) -> 185839.9 | I115: =H115/H17 -> 21.311915
B118: 10000 | D118: SPECIALTIES (Accessories/Fire Alarm/Hood)
B119: 10100 | D119: Bathroom Accessories | E119: 1.4 | F119: LS | G119: 980 | H119: =G119*E119 -> 1372 | J119: Includes 2 new ADA bathrooms on both floors
B120: 10200 | D120: Partitions/Showerpan | E120: 1 | F120: LS | G120: 9217 | H120: =E120*G120 -> 9217 | J120: Includes new shower pan, shower head and shower plumbing for the new shower room area
B121: 10300 | D121: New Hood/Exhaust/Fire Systems | E121: 0 | F121: LS | G121: 36334 | H121: =G121*E121 -> 0 | J121: NIC
B122: 10400 | D122: Fountain | E122: 0 | F122: LS | G122: 3000 | H122: =G122*E122 -> 0
B123: 10500 | D123: Fire Alarm | E123: 1 | F123: LS | G123: 7500 | H123: =G123*E123 -> 7500 | J123: Includes fire alarm systems for both floors
B124: 10600 | D124: FRP | E124: 0 | F124: LS | G124: 4412 | H124: =E124*G124 -> 0 | J124: .
J125: .
D126: Specialties Totals | H126: =SUM(H119:H124) -> 18089 | I126: =H126/H17 -> 2.0744266
B129: 11000 | D129: EQUIPMENT/WATER PROOFING
B130: 11005 | D130: Projector Screen/White board/Furniture | E130: 0 | F130: LS | G130: =2850+3620 -> 6470 | H130: =E130*G130 -> 0
B131: 11010 | D131: Fire extinghusier & Knox Box | E131: 2 | F131: LS | G131: 800 | H131: =E131*G131 -> 1600 | J131: Includes fire extingushier for the space per fire department standards
I133: =H133/H17 -> 0
D136: Equipment Totals | H136: =SUM(H130:H134) -> 1600 | I136: =H136/H17 -> 0.18348624
B139: 12000 | D139: FURNISHINGS/TRASH REMOVAL
B140: 12100 | D140: Trash Removal and Disposing | E140: 5.6 | F140: LS | G140: 2871 | H140: =E140*G140 -> 16077.6 | J140: Trash Dumps needed per city regulations. NO HAZMAT included
B141: 12100 | D141: Signs | F141: EA | H141: =E141*G141 -> 0
E142: 0 | F142: EA | G142: 900 | H142: =E142*G142 -> 0
D144: Furnishings Totals | H144: =SUM(H140:H142) -> 16077.6 | I144: =H144/H17 -> 1.8437615
D147: Conveying Systems Totals | H147: =SUM(H145:H145) -> 0 | I147: =H147/H17 -> 0
B150: 15000 | D150: MECHANICAL
...

Sheet General Conditions
C5: Project Duration:
C6: Projected Staff:
B9: ITEM | F9: UNIT | G9: TOTAL
B10: NO. | C10: DESCRIPTION | D10: QUANT | E10: UNIT | F10: COST | G10: COST
B12: SITE MANAGEMENT
B13: 1 | C13: Senior Project Manager | E13: WK | F13: =120*40 -> 4800 | G13: =D13*F13 -> 0
B14: 2 | C14: Project Manager | D14: 19 | E14: WK | F14: =55*30 -> 1650 | G14: =D14*F14*38% -> 11913
B15: 3 | C15: Assistant Project Manager | E15: WK | G15: =D15*F15 -> 0
B16: 4 | C16: Project Superintendant | D16: 16 | E16: WK | F16: =87*32 -> 2784 | G16: =D16*F16*38% -> 16926.72
B17: 5 | C17: Assistant Superintendant | E17: WK | G17: =D17*F17 -> 0
B18: 6 | C18: Project Engineer | E18: WK | G18: =D18*F18 -> 0
B19: 7 | C19: Assistant Project Engineer | E19: WK | G19: =D19*F19 -> 0
B20: 8 | C20: Form Detailer | E20: HR | G20: =D20*F20 -> 0
B21: 9 | C21: Project Secretary | E21: WK | G21: =D21*F21 -> 0
B22: 10 | C22: Project Accountant | D22: 7 | E22: MO | F22: =50*43 -> 2150 | G22: =D22*F22*38% -> 5719
B23: 11 | C23: MEP Coordinator | E23: HR | G23: =D23*F23 -> 0
B24: 12 | C24: EEO Coordinator | E24: WK | G24: =D24*F24 -> 0
B25: 13 | C25: Contract Administrator | E25: WK | G25: =D25*F25 -> 0
B26: 14 | C26: Safety Coordinator | D26: 88 | E26: HR | F26: 87 | G26: =D26*F26*38% -> 2909.28
B27: 15 | C27: Scheduling | E27: HR | F27: 65 | G27: =D27*F27 -> 0
B29: JOBSITE OFFICE
B30: 16 | C30: Office Rent | E30: MO | G30: =D30*F30 -> 0
B31: 17 | C31: Trailers | E31: MO | F31: 500 | G31: =D31*F31 -> 0
B32: 18 | C32: Site set-up / Mobilization (Move from trailer) | E32: LS | F32: 1500 | G32: =D32*F32 -> 0
B33: 19 | C33: Demobilization | E33: LS | F33: 3500 | G33: =D33*F33 -> 0
B34: 20 | C34: Jobsite Office Equipment / Furniture | E34: LS | F34: 1800 | G34: =D34*F34 -> 0
B35: 21 | C35: Office Supplies | E35: MO | F35: 125 | G35: =D35*F35 -> 0
B36: 22 | C36: Telephone / Fax | E36: LS | F36: 500 | G36: =D36*F36 -> 0
B37: 23 | C37: Telephone / Fax Monthly Operational Costs | E37: MO | F37: 125 | G37: =D37*F37 -> 0
B38: 24 | C38: Copier / Supplies / Maintenance | E38: MO | F38: 275 | G38: =D38*F38 -> 0
B39: 25 | C39: Project Sign | D39: 2 | E39: EA | F39: 225 | G39: =D39*F39*38% -> 171
B40: 26 | C40: Project Schedule | E40: MO | G40: =D40*F40 -> 0
B41: 27 | C41: Plan & Specification Printing (by Owner) | E41: LS | G41: =D41*F41 -> 0
B42: 28 | C42: Scaffolding | D42: 1 | E42: LS | F42: 720 | G42: =D42*F42*38% -> 273.6
B43: 29 | C43: Miscellaneous Reproduction | E43: LS | G43: =D43*F43 -> 0
B44: 30 | C44: Security | E44: MO | F44: 1250 | G44: =D44*F44 -> 0
B46: VEHICLES & TRAVEL
B47: 31 | C47: Truck Expense / Plant Vehicles | E47: MO | F47: 575 | G47: =D47*F47 -> 0
B48: 32 | C48: Gas / Oil | E48: MO | F48: 250 | G48: =D48*F48 -> 0
B49: 33 | C49: Miscellaneous Truck Repairs | E49: LS | G49: =D49*F49 -> 0
B50: 34 | C50: Generator | E50: WK | F50: 550 | G50: =D50*F50 -> 0
B52: EQUIPMENT & TOOLS
B53: 35 | C53: Project Tool Shed | E53: MO | G53: =D53*F53 -> 0
B54: 36 | C54: Small Tools | D54: 4 | E54: MO | F54: 125 | G54: =D54*F54*38% -> 190
B55: 37 | C55: Tools | E55: MO | F55: 100 | G55: =D55*F55 -> 0
B56: 38 | C56: Cranes | E56: LS | F56: 25000 | G56: =D56*F56 -> 0
B57: 39 | C57: Lifts | D57: 4 | E57: LS | F57: 650 | G57: =D57*F57*38% -> 988
B58: 40 | C58: Hoists | E58: LS | G58: =D58*F58 -> 0
B60: SAFETY & CLEAN-UP
B61: 41 | C61: Safety Inspections | D61: 5 | E61: HR | F61: 65 | G61: =D61*F61*38% -> 123.5
B62: 42 | C62: Interim Clean-up | D62: 14 | E62: HR | F62: 45 | G62: =D62*F62*38% -> 239.4
B63: 43 | C63: Debris Boxes | D63: 30 | E63: EA | F63: 560 | G63: =D63*F63*38% -> 6384
B64: 44 | C64: Site Fence (temp fence) | E64: LF | F64: 6.85 | G64: =D64*F64 -> 0
B65: 45 | C65: Temporary Walkway | E65: LF | F65: 25 | G65: =D65*F65 -> 0
B66: 46 | C66: Temporary Stairs | E66: LF | G66: =D66*F66 -> 0
B67: 47 | C67: Safety Rails | E67: LF | F67: 12 | G67: =D67*F67 -> 0
B68: 48 | C68: Street Barricades | E68: EA | F68: 65 | G68: =D68*F68 -> 0
B69: 49 | C69: Dumpsters | E69: EA | F69: 525 | G69: =D69*F69 -> 0
B70: 50 | C70: Final Clean-up (Own Forces) | E70: HR | F70: 58 | G70: =D70*F70 -> 0
B71: 51 | C71: Final Clean-up (Subcontractor) | D71: 1.2 | E71: LS | F71: =0.23*8000 -> 1840 | G71: =D71*F71*38% -> 839.04
B72: 52 | C72: Street Clean-up (by Subcontractor) | E72: LS | G72: =D72*F72 -> 0
B74: TEMPORARY SERVICES
B75: 53 | C75: Temporary Power Poles | E75: EA | F75: 2500 | G75: =D75*F75 -> 0
B76: 54 | C76: Temporary Power Poles Distribution | E76: EA | G76: =D76*F76 -> 0
B77: 55 | C77: Temporary Power Use | E77: MO | F77: 600 | G77: =D77*F77 -> 0
B78: 56 | C78: Temporary Water Hook-up | E78: EA | F78: 1850 | G78: =D78*F78 -> 0
B79: 57 | C79: Temporary Water Use | E79: MO | F79: 150 | G79: =D79*F79 -> 0
B80: 58 | C80: Temporary Phone Hook-up | E80: EA | F80: 1200 | G80: =D80*F80 -> 0
B81: 59 | C81: Bottled Water | E81: MO | F81: 75 | G81: =D81*F81 -> 0
B82: 60 | C82: Coffee Maker / Supplies Service | E82: MO | F82: 90 | G82: =D82*F82 -> 0
B83: 61 | C83: Temporary Lights | E83: MO | G83: =D83*F83 -> 0
B84: 62 | C84: Temporary Heat | E84: MO | G84: =D84*F84 -> 0
B85: 63 | C85: Temporary Toilets | E85: EA/MO | F85: 150 | G85: =D85*F85 -> 0
B87: SITE / BUILDING PROTECTION
B88: 64 | C88: Pump / Dewatering | E88: LS | G88: =D88*F88 -> 0
B89: 65 | C89: Dust Control (by Subcontractor) | E89: LS | G89: =D89*F89 -> 0
B90: 66 | C90: Building Signage and Handicap Sign | D90: 3 | E90: EA | F90: 380 | G90: =D90*F90*38% -> 433.2
B91: 67 | C91: Storm Water Pollution Program (SWPP) | E91: LS | F91: 2500 | G91: =D91*F91 -> 0
B93: OTHER
B94: 68 | C94: OSHA Requirements | E94: LS | G94: =D94*F94 -> 0
B95: 69 | C95: Project Photographs / Miscellaneous | E95: LS | G95: =D95*F95 -> 0
B96: 70 | C96: DUMPSTER | D96: 1 | E96: MO | F96: 920 | G96: =D96*F96 -> 920
B97: 71 | C97: Material Handling | E97: HR | F97: 58 | G97: =D97*F97 -> 0
B98: 72 | C98: Scaffold ( ) | E98: SF | G98: =D98*F98 -> 0
B99: 73 | C99: Final Audit | E99: LS | G99: =D99*F99 -> 0
B100: 74 | C100: Warranty Work / Call-back Allowance | E100: LS | G100: =D100*F100 -> 0
B101: 75 | C101: Parking for General Conditions | E101: LS | G101: =D101*F101 -> 0
B103: INSURANCE
B104: 76 | C104: Subguard | E104: LS | G104: =D104*F104 -> 0
B105: 77 | C105: Liability Insurance | E105: LS
B106: 78 | C106: Builder's Risk Insurance | E106: LS | G106: =D106*F106 -> 0
C110: General Conditions Total Cost | G110: =SUM(G11:G108) -> 48029.74

Sheet Off-Site Summary
A1: Project: | D1: ='Systems Summary'!D7 -> 356 S Daniel Way, San Jose, CA 95128 | E1: Project Type: | H1: ='Systems Summary'!I7 -> TI
A2: Location: | D2: ='Systems Summary'!D8 -> Close to Santana Row | E2: Structure Type: | H2: ='Systems Summary'!I8 -> Tilt Up
E3: No. Stories Below Grade: | H3: ='Systems Summary'!I9 -> NA
E4: No. Stories Above Grade: | H4: ='Systems Summary'!I10 -> 1
A5: Architect: | D5: ='Systems Summary'!D12 -> N/A | E5: No. of Units: | H5: ='Systems Summary'!I11 -> 2
E6: No. of Bathrooms: | H6: ='Systems Summary'!I12 -> 2
E7: Off-Site Area: | H7: ='Systems Summary'!I15 -> 0 | I7: SF
E8: Site Area: | H8: ='Systems Summary'!I16 -> 8720 | I8: SF
E9: ='Systems Summary'!F17 -> Lease Space/TI Area: | H9: ='Systems Summary'!I17 -> 8720 | I9: SF
E10: Common Area: | H10: ='Systems Summary'!I18 -> NA | I10: SF
E11: Unit Area: | H11: ='Systems Summary'!I19 -> NA | I11: SF
E12: Garage Area: | H12: ='Systems Summary'!I20 -> NA | I12: SF
B14: SPEC | G14: UNIT | H14: TOTAL | I14: COST
B15: SECT | D15: DESCRIPTION | E15: QUANT | F15: UNIT | G15: COST | H15: COST | I15: PER SF
B17: 01000 | D17: Temporary Construction | H17: ='Off-Site Detail'!H27 -> 0
B18: 02000 | D18: Site Work | H18: ='Off-Site Detail'!H65 -> 0
B19: 03000 | D19: Concrete | H19: ='Off-Site Detail'!H78 -> 0
B20: 04000 | D20: Masonry | H20: ='Off-Site Detail'!H88 -> 0
B21: 05000 | D21: Steel | H21: ='Off-Site Detail'!H98 -> 0
B22: 06000 | D22: Wood / Plastics | H22: ='Off-Site Detail'!H108 -> 0
B23: 07000 | D23: Thermal / Moisture Protection | H23: ='Off-Site Detail'!H118 -> 0
B24: 08000 | D24: Doors / Glass | H24: ='Off-Site Detail'!H128 -> 0
B25: 09000 | D25: Finishes | H25: ='Off-Site Detail'!H138 -> 0
B26: 10000 | D26: Specialties | H26: ='Off-Site Detail'!H148 -> 0
B27: 11000 | D27: Equipment | H27: ='Off-Site Detail'!H158 -> 0
B28: 12000 | D28: Furnishings | H28: ='Off-Site Detail'!H168 -> 0
B29: 13000 | D29: Special Construction (Water Fountain) | H29: ='Off-Site Detail'!H178 -> 0
B30: 14000 | D30: Conveying Systems | H30: ='Off-Site Detail'!H188 -> 0
B31: 15000 | D31: Mechanical | H31: ='Off-Site Detail'!H198 -> 0
B32: 16000 | D32: Electrical | H32: ='Off-Site Detail'!H208 -> 0
D35: Subtotal | H35: =SUM(H16:H33) -> 0
D37: General Conditions
D38: Builders Risk Insurance
D39: General Liability Insurance
D40: Bond
D41: Overhead
D42: Contractor's Fee
D45: Subtotal | H45: =SUM(H34:H43) -> 0
D47: Contractor's Contingency
D50: OFF-SITE TOTAL COST | H50: =SUM(H44:H48) -> 0

Sheet Off-Site Detail
A1: Project: | D1: ='Systems Summary'!D7 -> 356 S Daniel Way, San Jose, CA 95128 | E1: Project Type: | H1: ='Systems Summary'!I7 -> TI
A2: Location: | D2: ='Systems Summary'!D8 -> Close to Santana Row | E2: Structure Type: | H2: ='Systems Summary'!I8 -> Tilt Up
E3: No. Stories Below Grade: | H3: ='Systems Summary'!I9 -> NA
E4: No. Stories Above Grade: | H4: ='Systems Summary'!I10 -> 1
A5: Architect: | D5: ='Systems Summary'!D12 -> N/A | E5: No. of Units: | H5: ='Systems Summary'!I11 -> 2
E6: No. of Bathrooms: | H6: ='Systems Summary'!I12 -> 2
E7: Off-Site Area: | H7: ='Systems Summary'!I15 -> 0
E8: Site Area: | H8: ='Systems Summary'!I16 -> 8720
E9: ='Systems Summary'!F17 -> Lease Space/TI Area: | H9: ='Systems Summary'!I17 -> 8720 | I9: SF
E10: Common Area: | H10: ='Systems Summary'!I18 -> NA | I10: SF
E11: Unit Area: | H11: ='Systems Summary'!I19 -> NA | I11: SF
E12: ='Systems Summary'!F20 -> Garage Area: | H12: ='Systems Summary'!I20 -> NA
B14: SPEC | G14: UNIT | H14: TOTAL | I14: COST
B15: SECT | D15: DESCRIPTION | E15: QUANT | F15: UNIT | G15: COST | H15: COST | I15: PER SF
B17: 01000 | D17: TEMPORARY CONSTRUCTION
B18: 01100 | D18: Scaffold | F18: SF | H18: =E18*G18 -> 0
B19: 01150 | D19: Temporary roads | F19: SF | H19: =E19*G19 -> 0
B20: 01200 | D20: Barricades | F20: EA | H20: =E20*G20 -> 0
B21: 01250 | D21: Traffic control | F21: LS | H21: =E21*G21 -> 0
B22: 01260 | D22: Flagman | F22: LS | H22: =E22*G22 -> 0
B23: 01270 | D23: Safety rails | F23: LF | H23: =E23*G23 -> 0
D27: Temporary Construction Totals | H27: =SUM(H17:H25) -> 0 | I27: =H27/H9 -> 0
B30: 02000 | D30: SITE WORK
B31: 02050 | D31: Mobilizations | E31: 0 | F31: LS | G31: 5000 | H31: =E31*G31 -> 0
B32: 02100 | D32: Clear and grub | F32: SF | H32: =E32*G32 -> 0
B33: 02105 | D33: Protect (e) trees | F33: EA | H33: =E33*G33 -> 0
B34: 02150 | D34: Demolition | F34: SF | H34: =E34*G34 -> 0
B35: 02175 | D35: Dewatering | F35: SF | H35: =E35*G35 -> 0
B36: 02550 | D36: Site Utilities:
D37: Sanitary Sewer | F37: LF | H37: =E37*G37 -> 0
D38: Storm Drain | F38: LF | H38: =E38*G38 -> 0
D39: - 18" RCP | F39: LF | H39: =E39*G39 -> 0
D40: - 15" RCP | F40: LF | H40: =E40*G40 -> 0
D41: - 12" RCP | F41: LF | H41: =E41*G41 -> 0
D42: - 10" RCP | F42: LF | H42: =E42*G42 -> 0
D43: - 8" RCP | F43: LF | H43: =E43*G43 -> 0
D44: - 6" RCP | F44: LF | H44: =E44*G44 -> 0
D45: - Tie to (e) manhole | F45: LS | H45: =E45*G45 -> 0
D46: - Catch basins | F46: EA | H46: =E46*G46 -> 0
D47: - Curb inlets | F47: EA | H47: =E47*G47 -> 0
D48: - Drain inlets | F48: EA | H48: =E48*G48 -> 0
... D53: Gas Service | F53: LF | H53: =E53*G53 -> 0
B54: 02620 | D54: AC Paving
D55: 3" AC over 5" AB | F55: SF | H55: =E55*G55 -> 0
D56: 3" AC over 6" AB | F56: SF | H56: =E56*G56 -> 0
D57: 3" AC over 9" AB | F57: SF | H57: =E57*G57 -> 0
B58: 02636 | D58: Water Features (Allowance) | F58: LS | H58: =E58*G58 -> 0
B59: 02750 | D59: Landscape Irrigation | F59: SF | H59: =E59*G59 -> 0
B60: 02800 | D60: Landscape Planting | F60: SF | H60: =E60*G60 -> 0
B61: 02800 | D61: Trees | F61: EA | H61: =E61*G61 -> 0
D65: Site Work Totals | H65: =SUM(H31:H63) -> 0 | I65: =H65/H9 -> 0
B68: 03000 | D68: CONCRETE
B69: 03630 | D69: City Standard 4" Sidewalk | F69: SF | H69: =E69*G69 -> 0
B70: 03630 | D70: City Standard Curb and Gutter | F70: LF | H70: =E70*G70 -> 0
B71: 03630 | D71: 6" Curb | F71: LF | H71: =E71*G71 -> 0
B72: 03630 | D72: Valley Gutter | F72: SF | H72: =E72*G72 -> 0
B73: 03650 | D73: Retaining wall | F73: SF | H73: =E73*G73 -> 0
D78: Concrete Totals | H78: =SUM(H69:H76) -> 0 | I78: =H78/H9 -> 0
B81: 04000 | D81: MASONRY
B82: 04100 | D82: 8" CMU Wall (standard block) | F82: SF | H82: =E82*G82 -> 0
B83: 04150 | D83: CMU Retaining wall | F83: SF | H83: =E83*G83 -> 0
D88: Masonry Totals | H88: =SUM(H82:H86) -> 0 | I88: =H88/H9 -> 0
B91: 05000 | D91: STEEL
B92: 05100 | D92: Pipe bollards | H92: =E92*G92 -> 0
D98: Steel Totals | H98: =SUM(H92:H96) -> 0 | I98: =H98/H9 -> 0
B101: 06000 | D101: WOOD / PLASTICS
B102: 06100 | D102: Wood fence | F102: SF | H102: =E102*G102 -> 0
B103: 06100 | D103: Wood gate | F103: EA | H103: =E103*G103 -> 0
D108: Wood / Plastics Totals | H108: =SUM(H102:H106) -> 0 | I108: =H108/H9 -> 0
B111: 07000 | D111: THERMAL / MOISTURE PROTECT
D118: Thermal / Moisture Protect Totals | H118: =SUM(H112:H116) -> 0 | I118: =H118/H9 -> 0
B121: 08000 | D121: DOORS / GLASS
B122: 08100 | D122: HM door / HM frame / hardware
B123: 08150
D128: Doors / Glass Totals | H128: =SUM(H122:H126) -> 0 | I128: =H128/H9 -> 0
B131: 09000 | D131: FINISHES
D138: Finishes Totals | H138: =SUM(H132:H136) -> 0 | I138: =H138/H9 -> 0
B141: 10000 | D141: SPECIALTIES
D148: Specialties Totals | H148: =SUM(H142:H146) -> 0 | I148: =H148/H9 -> 0
B151: 11000 | D151: EQUIPMENT
D158: Equipment Totals | H158: =SUM(H152:H156) -> 0 | I158: =H158/H9 -> 0
B161: 12000 | D161: FURNISHINGS
D168: Furnishings Totals | H168: =SUM(H162:H166) -> 0 | I168: =H168/H9 -> 0
B171: 13000 | D171: SPECIAL CONSTRUCTION
D178: Special Construction Totals | H178: =SUM(H172:H176) -> 0 | I178: =H178/H9 -> 0
B181: 14000 | D181: CONVEYING SYSTEMS
D188: Conveying Systems Totals | H188: =SUM(H182:H186) -> 0 | I188: =H188/H9 -> 0
B191: 15000 | D191: MECHANICAL
D198: Mechanical Totals | H198: =SUM(H192:H196) -> 0 | I198: =H198/H9 -> 0
B201: 16000 | D201: ELECTRICAL
B202: 16000 | D202: Off-site vaults | F202: EA | H202: =E202*G202 -> 0
B203: 16900 | D203: Electrical service | F203: LS | H203: =E203*G203 -> 0
B204: 16900 | D204: Street Lighting | F204: EA | H204: =E204*G204 -> 0
B205: 16900 | D205: Landscape Lighting | F205: SF | H205: =E205*G205 -> 0
D208: Electrical Totals | H208: =SUM(H202:H206) -> 0 | I208: =H208/H9 -> 0
D212: Off-Site Work Subtotal | H212: =SUM(H27+H65+H78+H88+H98+H108+H118+H128+H138+H148+H158+H168+H178+H188+H198+H208) -> 0 | I212: =H212/H9 -> 0

Sheet Site Summary
A1: Project: | D1: ='Systems Summary'!D7 -> 356 S Daniel Way, San Jose, CA 95128 | E1: Project Type: | H1: ='Systems Summary'!I7 -> TI
A2: Location: | D2: ='Systems Summary'!D8 -> Close to Santana Row | E2: Structure Type: | H2: ='Systems Summary'!I8 -> Tilt Up
E3: No. Stories Below Grade: | H3: ='Systems Summary'!I9 -> NA
E4: No. Stories Above Grade: | H4: ='Systems Summary'!I10 -> 1
A5: Architect: | D5: ='Systems Summary'!D12 -> N/A | E5: No. of Units: | H5: ='Systems Summary'!I11 -> 2
D6: ='Systems Summary'!D15 -> 0 | E6: No. of Bathrooms: | H6: ='Systems Summary'!I12 -> 2
E7: Off-Site Area: | H7: ='Systems Summary'!I15 -> 0 | I7: SF
E8: Site Area: | H8: ='Systems Summary'!I16 -> 8720 | I8: SF
E9: ='Systems Summary'!F17 -> Lease Space/TI Area: | H9: ='Systems Summary'!I17 -> 8720 | I9: SF
E10: Common Area: | H10: ='Systems Summary'!I18 -> NA | I10: SF
E11: Unit Area: | H11: ='Systems Summary'!I19 -> NA | I11: SF
E12: Garage Area: | H12: ='Systems Summary'!I20 -> NA | I12: SF
B14: SPEC | G14: UNIT | H14: TOTAL | I14: COST
B15: SECT | D15: DESCRIPTION | E15: QUANT | F15: UNIT | G15: COST | H15: COST | I15: PER SF
B17: 01000 | D17: Temporary Construction | H17: ='Site Detail'!H27 -> 0
B18: 02000 | D18: Site Work | H18: ='Site Detail'!H67 -> 0
B19: 03000 | D19: Concrete | H19: ='Site Detail'!H84 -> 0
B20: 04000 | D20: Masonry | H20: ='Site Detail'!H94 -> 0
B21: 05000 | D21: Steel | H21: ='Site Detail'!H104 -> 0
B22: 06000 | D22: Wood / Plastics | H22: ='Site Detail'!H114 -> 0
B23: 07000 | D23: Thermal / Moisture Protection | H23: ='Site Detail'!H124 -> 0
B24: 08000 | D24: Doors / Glass | H24: ='Site Detail'!H134 -> 0
B25: 09000 | D25: Finishes | H25: ='Site Detail'!H144 -> 0
B26: 10000 | D26: Specialties | H26: ='Site Detail'!H154 -> 0
B27: 11000 | D27: Equipment | H27: ='Site Detail'!H164 -> 0
B28: 12000 | D28: Furnishings | H28: ='Site Detail'!H174 -> 0
B29: 13000 | D29: Special Construction | H29: ='Site Detail'!H184 -> 0
B30: 14000 | D30: Conveying Systems | H30: ='Site Detail'!H194 -> 0
B31: 15000 | D31: Mechanical | H31: ='Site Detail'!H204 -> 0
B32: 16000 | D32: Electrical | H32: ='Site Detail'!H216 -> 0
D35: Subtotal | H35: =SUM(H16:H33) -> 0
D37: General Conditions
D38: Builders Risk Insurance
D39: General Liability Insurance
D40: Bond
D41: Overhead
D42: Contractor's Fee
D45: Subtotal | H45: =SUM(H34:H43) -> 0
D47: Contractor's Contingency
D50: SITE TOTAL COST | H50: =SUM(H44:H48) -> 0

Sheet Site Detail
A1: Project: | D1: ='Systems Summary'!D7 -> 356 S Daniel Way, San Jose, CA 95128 | E1: Project Type: | H1: ='Systems Summary'!I7 -> TI
A2: Location: | D2: ='Systems Summary'!D8 -> Close to Santana Row | E2: Structure Type: | H2: ='Systems Summary'!I8 -> Tilt Up
E3: No. Stories Below Grade: | H3: ='Systems Summary'!I9 -> NA
E4: No. Stories Above Grade: | H4: ='Systems Summary'!I10 -> 1
A5: Architect: | D5: ='Systems Summary'!D12 -> N/A | E5: No. of Units: | H5: ='Systems Summary'!I11 -> 2
D6: ='Systems Summary'!D15 -> 0 | E6: No. of Bathrooms: | H6: ='Systems Summary'!I12 -> 2
E7: Off-Site Area: | H7: ='Systems Summary'!I15 -> 0 | I7: SF
E8: Site Area: | H8: ='Systems Summary'!I16 -> 8720 | I8: SF
E9: ='Systems Summary'!F17 -> Lease Space/TI Area: | H9: ='Systems Summary'!I17 -> 8720 | I9: SF
E10: Common Area: | H10: ='Systems Summary'!I18 -> NA | I10: SF
E11: Unit Area: | H11: ='Systems Summary'!I19 -> NA | I11: SF
E12: Garage Area: | H12: ='Systems Summary'!I20 -> NA | I12: SF
B14: SPEC | G14: UNIT | H14: TOTAL | I14: COST
B15: SECT | D15: DESCRIPTION | E15: QUANT | F15: UNIT | G15: COST | H15: COST | I15: PER SF
B17: 01000 | D17: TEMPORARY CONSTRUCTION
B18: 01100 | D18: Scaffold | F18: SF | H18: =E18*G18 -> 0
B19: 01150 | D19: Temporary roads | F19: SF | H19: =E19*G19 -> 0
B20: 01200 | D20: Barricades | F20: EA | G20: 65 | H20: =E20*G20 -> 0
B21: 01250 | D21: Traffic control | F21: LS | G21: 2500 | H21: =E21*G21 -> 0
B22: 01260 | D22: Flagman | F22: LS | H22: =E22*G22 -> 0
B23: 01270 | D23: Safety rails | F23: LF | H23: =E23*G23 -> 0
D27: Temporary Construction Totals | H27: =SUM(H17:H25) -> 0 | I27: =H27/H9 -> 0
B30: 02000 | D30: SITE WORK
B31: 02050 | D31: Mobilizations | F31: LS | G31: 5000 | H31: =E31*G31 -> 0
B32: 02100 | D32: Clear and grub | F32: SF | G32: 1 | H32: =E32*G32 -> 0
B33: 02105 | D33: Protect (e) trees | F33: EA | H33: =E33*G33 -> 0
B34: 02150 | D34: Demolition | F34: SF | G34: 1.5 | H34: =E34*G34 -> 0
B35: 02175 | D35: Dewatering | F35: SF | H35: =E35*G35 -> 0
B36: 02550 | D36: Site Utilities:
D37: Sanitary Sewer | F37: LS | G37: 10000 | H37: =E37*G37 -> 0
D38: - Tie to (e) manhole | F38: LS | G38: 2000 | H38: =E38*G38 -> 0
D39: Storm Drain | F39: LS | G39: 15000 | H39: =E39*G39 -> 0
D40: - 18" RCP | F40: LF | H40: =E40*G40 -> 0
D41: - 15" RCP | F41: LF | H41: =E41*G41 -> 0
D42: - 12" RCP | F42: LF | H42: =E42*G42 -> 0
D43: - 10" RCP | F43: LF | H43: =E43*G43 -> 0
D44: - 8" RCP | F44: LF | H44: =E44*G44 -> 0
D45: - 6" RCP | F45: LF | H45: =E45*G45 -> 0
D46: - Tie to (e) manhole | F46: LS | G46: 1500 | H46: =E46*G46 -> 0
D47: - Catch basins | F47: EA | H47: =E47*G47 -> 0
D48: - Curb inlets | F48: EA | H48: =E48*G48 -> 0
D49: - Drain inlets | F49: EA | H49: =E49*G49 -> 0
D50: Domestic Water | F50: LF | H50: =E50*G50 -> 0
D52: Fire Water | F52: LS | G52: 10000 | H52: =E52*G52 -> 0
D54: Gas Service | F54: LS | G54: 7500 | H54: =E54*G54 -> 0
B55: 02620 | D55: AC Paving
D56: 3" AC over 5" AB | F56: SF | H56: =E56*G56 -> 0
D57: 3" AC over 6" AB | F57: SF | H57: =E57*G57 -> 0
D58: 3" AC over 9" AB | F58: SF | H58: =E58*G58 -> 0
B59: 02636 | D59: Water Features (Allowance) | F59: LS | H59: =E59*G59 -> 0
B60: 02750 | D60: Landscape Irrigation | F60: SF | G60: 1.25 | H60: =E60*G60 -> 0
B61: 02800 | D61: Landscape Planting | F61: SF | G61: 1.55 | H61: =E61*G61 -> 0
B62: 02800 | D62: Trees | F62: EA | G62: 495 | H62: =E62*G62 -> 0
B63: 02800 | D63: Tree grates | F63: EA | G63: 600 | H63: =E63*G63 -> 0
D67: Site Work Totals | H67: =SUM(H30:H65) -> 0 | I67: =H67/H9 -> 0
B70: 03000 | D70: CONCRETE
B71: 03630 | D71: City Standard 4" Sidewalk | F71: SF | G71: 6.25 | H71: =E71*G71 -> 0
B72: 03630 | D72: City Standard Curb and Gutter | F72: LF | G72: 12 | H72: =E72*G72 -> 0
B73: 03630 | D73: 6" Curb | F73: LF | H73: =E73*G73 -> 0
B74: 03630 | D74: Valley Gutter | F74: SF | H74: =E74*G74 -> 0
B75: 03650 | D75: Retaining wall | F75: SF | G75: 22.5 | H75: =E75*G75 -> 0
B76: 03660 | D76: Driveway approach | F76: EA | G76: 5000 | H76: =E76*G76 -> 0
B77: 03670 | D77: Concrete Ramps | F77: SF | G77: 9.25 | H77: =E77*G77 -> 0
B78: 03680 | D78: Site Stairs | F78: RSR | G78: 250 | H78: =E78*G78 -> 0
B79: 03690 | D79: Concrete Paving | F79: SF | G79: 15 | H79: =E79*G79 -> 0
B80: 03700 | D80: Courtyard Concrete Paving | F80: SF | G80: 18.5 | H80: =E80*G80 -> 0
B81: 03710 | D81: Courtyard Entry Stairs | F81: RSR | G81: 400 | H81: =E81*G81 -> 0
D84: Concrete Totals | H84: =SUM(H71:H82) -> 0 | I84: =H84/H9 -> 0
B87: 04000 | D87: MASONRY
B88: 04100 | D88: 8" CMU Wall (standard block) | F88: SF | H88: =E88*G88 -> 0
B89: 04150 | D89: CMU Retaining wall | F89: SF | H89: =E89*G89 -> 0
D94: Masonry Totals | H94: =SUM(H88:H92) -> 0 | I94: =H94/H9 -> 0
B97: 05000 | D97: STEEL
B98: 05100 | D98: Pipe bollards | F98: EA | H98: =E98*G98 -> 0
B99: 05200 | D99: Single Rail Handrail | F99: LF | G99: 25 | H99: =E99*G99 -> 0
B100: 05300 | D100: Wrought Iron Fence | F100: LF
D104: Steel Totals | H104: =SUM(H98:H102) -> 0 | I104: =H104/H9 -> 0
B107: 06000 | D107: WOOD / PLASTICS
B108: 06100 | D108: Rough Framing | F108: SF | H108: =E108*G108 -> 0
B109: 06200 | D109: Site Wood Fence | F109: LF | G109: 22.5 | H109: =E109*G109 -> 0
B110: 06300 | D110: Decorative Wood Gate | F110: EA | H110: =E110*G110 -> 0
B111: 06400 | D111: Wood Trellis | F111: SF | H111: =E111*G111 -> 0
D114: Wood / Plastics Totals | H114: =SUM(H108:H112) -> 0 | I114: =H114/H9 -> 0
B117: 07000 | D117: THERMAL / MOISTURE PROTECT
B118: 07100 | D118: Bentonite Waterproofing | F118: SF | H118: =E118*G118 -> 0
B119: 07200 | D119: Paraseal Waterproofing | F119: SF | H119: =E119*G119 -> 0
B120: 07300 | D120: Caulking and Sealants | F120: LS | H120: =E120*G120 -> 0
D124: Thermal / Moisture Protect Totals | H124: =SUM(H118:H122) -> 0 | I124: =H124/H9 -> 0
B127: 08000 | D127: DOORS / GLASS
B128: 08100 | D128: Exterior HM Door / Frame / Hardware | F128: EA | H128: =E128*G128 -> 0
B129: 08200 | D129: Misc. Iron Gate | F129: EA | H129: =E129*G129 -> 0
B130: 08300 | D130: Specialty Doors | F130: EA | H130: =E130*G130 -> 0
D134: Doors / Glass Totals | H134: =SUM(H128:H132) -> 0 | I134: =H134/H9 -> 0
B137: 09000 | D137: FINISHES
B138: 09100 | D138: Stucco / Plaster | F138: SF | H138: =E138*G138 -> 0
B139: 09200 | D139: Drywall | F139: SF | H139: =E139*G139 -> 0
B140: 09900 | D140: Paint | F140: SF | H140: =E140*G140 -> 0
D144: Finishes Totals | H144: =SUM(H138:H142) -> 0 | I144: =H144/H9 -> 0
B147: 10000 | D147: SPECIALTIES
D154: Specialties Totals | H154: =SUM(H148:H152) -> 0 | I154: =H154/H9 -> 0
...

Sheet Garage Summary
A1: Project: | D1: ='Systems Summary'!D7 -> 356 S Daniel Way, San Jose, CA 95128 | E1: Project Type: | H1: ='Systems Summary'!I7 -> TI
A2: Location: | D2: ='Systems Summary'!D8 -> Close to Santana Row | E2: Structure Type: | H2: ='Systems Summary'!I8 -> Tilt Up
E3: No. Stories Below Grade: | H3: ='Systems Summary'!I9 -> NA
E4: No. Stories Above Grade: | H4: ='Systems Summary'!I10 -> 1
A5: Architect: | D5: ='Systems Summary'!D12 -> N/A | E5: No. of Units: | H5: ='Systems Summary'!I11 -> 2
E6: No. of Bathrooms: | H6: ='Systems Summary'!I12 -> 2
E7: Off-Site Area: | H7: ='Systems Summary'!I15 -> 0 | I7: SF
E8: Site Area: | H8: ='Systems Summary'!I16 -> 8720 | I8: SF
E9: ='Systems Summary'!F17 -> Lease Space/TI Area: | H9: ='Systems Summary'!I17 -> 8720 | I9: SF
E10: Common Area: | H10: ='Systems Summary'!I18 -> NA | I10: SF
E11: Unit Area: | H11: ='Systems Summary'!I19 -> NA | I11: SF
E12: Garage Area: | H12: ='Systems Summary'!I20 -> NA | I12: SF
B14: SPEC | G14: UNIT | H14: TOTAL | I14: COST
B15: SECT | D15: DESCRIPTION | E15: QUANT | F15: UNIT | G15: COST | H15: COST | I15: PER SF
B17: 01000 | D17: Temporary Construction | H17: ='Garage Detail'!H27 -> 0
B18: 02000 | D18: Site Work | H18: ='Garage Detail'!H65 -> 0
B19: 03000 | D19: Concrete | H19: ='Garage Detail'!H79 -> 0
B20: 04000 | D20: Masonry | H20: ='Garage Detail'!H89 -> 0
B21: 05000 | D21: Steel | H21: ='Garage Detail'!H101 -> 0
B22: 06000 | D22: Wood / Plastics | H22: ='Garage Detail'!H114 -> 0
B23: 07000 | D23: Thermal / Moisture Protection | H23: ='Garage Detail'!H131 -> 0
B24: 08000 | D24: Doors / Glass | H24: ='Garage Detail'!H141 -> 0
B25: 09000 | D25: Finishes | H25: ='Garage Detail'!H178 -> 0
B26: 10000 | D26: Specialties | H26: ='Garage Detail'!H188 -> 0
B27: 11000 | D27: Equipment | H27: ='Garage Detail'!H198 -> 0
B28: 12000 | D28: Furnishings | H28: ='Garage Detail'!H207 -> 0
B29: 13000 | D29: Special Construction | H29: ='Garage Detail'!H216 -> 0
B30: 14000 | D30: Conveying Systems | H30: ='Garage Detail'!H227 -> 0
B31: 15000 | D31: Mechanical | H31: ='Garage Detail'!H241 -> 0
B32: 16000 | D32: Electrical | H32: ='Garage Detail'!H256 -> 0
D35: Subtotal | H35: =SUM(H16:H33) -> 0
D37: General Conditions
D38: Builders Risk Insurance
D39: General Liability Insurance
D40: Bond
D41: Overhead
D42: Contractor's Fee
D45: Subtotal | H45: =SUM(H34:H43) -> 0
D47: Contractor's Contingency
D50: GARAGE TOTAL COST | H50: =SUM(H44:H48) -> 0

Sheet Garage Detail
A1: Project: | D1: ='Systems Summary'!D7 -> 356 S Daniel Way, San Jose, CA 95128 | E1: Project Type: | H1: ='Systems Summary'!I7 -> TI
A2: Location: | D2: ='Systems Summary'!D8 -> Close to Santana Row | E2: Structure Type: | H2: ='Systems Summary'!I8 -> Tilt Up
E3: No. Stories Below Grade: | H3: ='Systems Summary'!I9 -> NA
E4: No. Stories Above Grade: | H4: ='Systems Summary'!I10 -> 1
A5: Architect: | D5: ='Systems Summary'!D12 -> N/A | E5: No. of Units: | H5: ='Systems Summary'!I11 -> 2
E6: No. of Bathrooms: | H6: ='Systems Summary'!I12 -> 2
E7: Off-Site Area: | H7: ='Systems Summary'!I15 -> 0 | I7: SF
E8: Site Area: | H8: ='Systems Summary'!I16 -> 8720 | I8: SF
E9: ='Systems Summary'!F17 -> Lease Space/TI Area: | H9: ='Systems Summary'!I17 -> 8720 | I9: SF
E10: Common Area: | H10: ='Systems Summary'!I18 -> NA | I10: SF
E11: Unit Area: | H11: ='Systems Summary'!I19 -> NA | I11: SF
E12: Garage Area: | H12: ='Systems Summary'!I20 -> NA | I12: SF
B14: SPEC | G14: UNIT | H14: TOTAL | I14: COST
B15: SECT | D15: DESCRIPTION | E15: QUANT | F15: UNIT | G15: COST | H15: COST | I15: PER SF
B17: 01000 | D17: TEMPORARY CONSTRUCTION
B18: 01100 | D18: Scaffold | F18: SF | H18: =E18*G18 -> 0
B19: 01150 | D19: Temporary roads | F19: SF | H19: =E19*G19 -> 0
B20: 01200 | D20: Barricades | F20: EA | G20: 65 | H20: =E20*G20 -> 0
B21: 01250 | D21: Traffic control | F21: LS | G21: 4000 | H21: =E21*G21 -> 0
B22: 01260 | D22: Flagman | F22: LS | G22: 1200 | H22: =E22*G22 -> 0
B23: 01270 | D23: Safety rails | F23: LF | H23: =E23*G23 -> 0
D27: Temporary Construction Totals | H27: =SUM(H17:H25) -> 0 | I27: =H27/H9 -> 0
B30: 02000 | D30: SITE WORK
B31: 02050 | D31: Mobilizations | F31: LS | G31: 5000 | H31: =E31*G31 -> 0
B32: 02100 | D32: Clear and grub | F32: SF | H32: =E32*G32 -> 0
B33: 02105 | D33: Protect (e) trees | F33: EA | H33: =E33*G33 -> 0
B34: 02150 | D34: Demolition | F34: SF | H34: =E34*G34 -> 0
B35: 02175 | D35: Dewatering | F35: SF | H35: =E35*G35 -> 0
B36: 02550 | D36: Site Utilities:
D37: Sanitary Sewer | F37: LF | H37: =E37*G37 -> 0
D38: Storm Drain | F38: LF | H38: =E38*G38 -> 0
D39: - 18" RCP | F39: LF | H39: =E39*G39 -> 0
D40: - 15" RCP | F40: LF | H40: =E40*G40 -> 0
D41: - 12" RCP | F41: LF | H41: =E41*G41 -> 0
D42: - 10" RCP | F42: LF | H42: =E42*G42 -> 0
D43: - 8" RCP | F43: LF | H43: =E43*G43 -> 0
D44: - 6" RCP | F44: LF | H44: =E44*G44 -> 0
D45: - Tie to (e) manhole | F45: LS | H45: =E45*G45 -> 0
D46: - Catch basins | F46: EA | H46: =E46*G46 -> 0
D47: - Curb inlets | F47: EA | H47: =E47*G47 -> 0
D48: - Drain inlets | F48: EA | H48: =E48*G48 -> 0
... D53: Gas Service | F53: LF | H53: =E53*G53 -> 0
B54: 02620 | D54: AC Paving
D55: 3" AC over 5" AB | F55: SF | H55: =E55*G55 -> 0
D56: 3" AC over 6" AB | F56: SF | H56: =E56*G56 -> 0
D57: 3" AC over 9" AB | F57: SF | H57: =E57*G57 -> 0
B58: 02636 | D58: Water Features (Allowance) | F58: LS | H58: =E58*G58 -> 0
B59: 02750 | D59: Landscape Irrigation | F59: SF | H59: =E59*G59 -> 0
B60: 02800 | D60: Landscape Planting | F60: SF | H60: =E60*G60 -> 0
B61: 02800 | D61: Trees | F61: EA | H61: =E61*G61 -> 0
D65: Site Work Totals | H65: =SUM(H30:H63) -> 0 | I65: =H65/H9 -> 0
B68: 03000 | D68: CONCRETE
B69: 03300 | D69: 2-Story PIP Concrete Garage Structure | F69: SF | G69: 31.45 | H69: =E69*G69 -> 0
B70: 03600 | D70: Spread Footing Foundations | F70: CY | G70: 650 | H70: =E70*G70 -> 0
B71: 03700 | D71: PIP Walls | F71: SF | G71: 8.4 | H71: =E71*G71 -> 0
B72: 03750 | D72: PIP Columns | F72: CY | G72: 2100 | H72: =E72*G72 -> 0
B73: 03780 | D73: Concrete Stairs | F73: RSR | G73: 250 | H73: =E73*G73 -> 0
B74: 03700 | D74: Retaining wall | F74: CY | G74: 565 | H74: =E74*G74 -> 0
B75: 03800 | D75: Masonry wall footings | F75: CY | G75: 595 | H75: =E75*G75 -> 0
D79: Concrete Totals | H79: =SUM(H69:H77) -> 0 | I79: =H79/H9 -> 0
B82: 04000 | D82: MASONRY
B83: 04100 | D83: 8" CMU Wall (standard block) | F83: SF | G83: 13.75 | H83: =E83*G83 -> 0
B84: 04150 | D84: CMU Retaining wall | F84: SF | H84: =E84*G84 -> 0
D89: Masonry Totals | H89: =SUM(H83:H87) -> 0 | I89: =H89/H9 -> 0
B92: 05000 | D92: STEEL
B93: 05100 | D93: Pipe bollards | F93: EA | G93: 750 | H93: =E93*G93 -> 0
B94: 05500 | D94: Structural Steel | F94: LS | H94: =E94*G94 -> 0
B95: 05700 | D95: Single Rail Pipe Handrails | F95: LF | G95: 35 | H95: =E95*G95 -> 0
B96: 05800 | D96: Multi-Rail Pipe Handrails | F96: LF | G96: 58 | H96: =E96*G96 -> 0
D101: Steel Totals | H101: =SUM(H93:H99) -> 0 | I101: =H101/H9 -> 0
B104: 06000 | D104: WOOD / PLASTICS
B105: 06100 | D105: Rough Framing | F105: SF | H105: =E105*G105 -> 0
B106: 06200 | D106: Wood Stairs | F106: RISER | H106: =E106*G106 -> 0
B107: 06500 | D107: Finish Carpentry | F107: SF | H107: =E107*G107 -> 0
B108: 06800 | D108: Window Apron, Sills and/or Trim | F108: UNIT | H108: =E108*G108 -> 0
B109: 06900 | D109: Wood Base | F109: LF | H109: =E109*G109 -> 0
D114: Wood / Plastics Totals | H114: =SUM(H105:H112) -> 0 | I114: =H114/H9 -> 0
B117: 07000 | D117: THERMAL / MOISTURE PROTECT
B118: 07100 | D118: Building Insulation | F118: SF | H118: =E118*G118 -> 0
B119: 07200 | D119: Exterior Wall Insulation | F119: SFCA | H119: =E119*G119 -> 0
B120: 07250 | D120: Interior Wall Insulation | F120: SFCA | H120: =E120*G120 -> 0
B121: 07270 | D121: Floor / Ceiling Insulation | F121: SF | H121: =E121*G121 -> 0
B122: 07300 | D122: Waterproofing | F122: SF | H122: =E122*G122 -> 0
B123: 07400 | D123: Composition Roof | F123: SF | H123: =E123*G123 -> 0
B124: 07450 | D124: Built-up Roof | F124: SF | H124: =E124*G124 -> 0
B125: 07500 | D125: Asphalt Shingle Roof | F125: SF | H125: =E125*G125 -> 0
B126: 07550 | D126: Concrete Roof Tiles | F126: SF | H126: =E126*G126 -> 0
B127: 07900 | D127: Caulking and Sealants | F127: LS | H127: =E127*G127 -> 0
H128: =E128*G128 -> 0
D131: Thermal / Moisture Protect Totals | H131: =SUM(H118:H129) -> 0 | I131: =H131/H9 -> 0
B134: 08000 | D134: DOORS / GLASS
B135: 08100 | D135: Exterior Doors / Frames / Hardware | F135: EA
B136: 08130
D141: Doors / Glass Totals | H141: =SUM(H135:H139) -> 0 | I141: =H141/H9 -> 0
B144: 09000 | D144: FINISHES
B145: 09100 | D145: Stucco / Plaster | F145: SF | H145: =E145*G145 -> 0
B146: 09120 | D146: Stucco soffits at decks | F146: SF | H146: =E146*G146 -> 0
B147: 09140 | D147: Plaster | F147: SF | H147: =E147*G147 -> 0
B148: 09150 | D148: Plaster soffits at decks | F148: SF | H148: =E148*G148 -> 0
B149: 09200 | D149: Drywall | F149: SF | G149: 6.85 | H149: =E149*G149 -> 0
...

Sheet Takeoffs
A2: SPEC
A3: DIV | B3: NO. | C3: DESCRIPTION | E3: QUANTITY | F3: UNITS | G3: REMARKS
A5: 00000 | C5: AREA CALCULATIONS
C6: Site Area | F6: SF
C7: Garage Common Area | F7: SF
C8: First Floor Common Area | F8: SF | G8: Say 1,000 SF
C9: Second Floor Common Area | F9: SF | G9: Say 1,000 SF
C10: Third Floor Common Area | F10: SF | G10: Say 1,000 SF
C11: Fourth Floor Common Area | F11: SF
C12: Total Common Area | F12: SF
C14: First Floor Net Area | F14: SF
C15: Second Floor Unit Net Area | F15: SF
C16: Third Floor Unit Net Area | F16: SF
C17: Fourth Floor Unit Net Area | F17: SF
C18: Total Unit Area | F18: SF
C20: LANDSCAPING
C21: Landscaping and irrigation area | F21: SF
C23: SPREAD FOOTINGS
C24: PIP Column Footings @ Garage | F24: CY
C25: Perimeter Building Footings | F25: CY
C26: Interior Footings @ CMU Walls | F26: CY
C28: SUSPENDED 1st FLOOR CONCRETE DECK
C29: Assume 10" suspended slab
